{
    "node_types": [
        "invoice",
        "sku",
        "zone"
    ],
    "edge_types": [
        "('invoice', 'requires', 'sku')",
        "('sku', 'located_at', 'zone')",
        "('sku', 'rev_requires', 'invoice')",
        "('zone', 'rev_located_at', 'sku')"
    ],
    "num_invoices": 27,
    "num_sku": 90,
    "num_zone": 5,
    "invoices": [
        [
            79,
            4,
            85,
            8,
            20,
            72,
            65,
            73
        ],
        [
            6,
            36,
            3,
            27,
            11,
            57,
            49,
            32,
            42,
            49,
            24,
            60,
            69,
            53
        ],
        [
            57,
            36,
            37,
            77,
            76,
            35,
            73,
            18,
            15,
            72
        ],
        [
            17,
            25,
            15,
            85,
            84,
            32,
            83,
            67,
            31,
            36
        ],
        [
            27,
            22,
            82,
            28,
            10
        ],
        [
            47,
            5,
            53,
            52,
            11,
            33,
            37
        ],
        [
            64,
            54,
            42,
            7,
            39,
            86,
            68
        ],
        [
            86,
            66,
            24,
            88,
            9,
            46,
            25,
            42,
            52,
            53
        ],
        [
            24,
            71,
            21,
            76,
            35,
            26,
            21,
            72,
            83,
            2,
            47,
            63,
            75,
            37
        ],
        [
            74,
            4,
            22,
            43,
            45,
            59,
            80,
            18,
            68,
            27,
            89,
            76,
            15
        ],
        [
            18,
            23,
            17,
            75,
            14,
            44,
            0,
            15
        ],
        [
            33,
            28,
            79,
            55,
            7,
            34,
            67,
            63,
            19
        ],
        [
            13,
            1,
            50,
            63,
            11,
            41,
            47,
            10,
            61,
            64,
            51,
            77
        ],
        [
            53,
            83,
            28,
            29,
            20,
            58,
            63,
            74,
            46,
            64,
            13,
            58
        ],
        [
            7,
            33,
            6,
            0,
            17,
            16,
            26,
            49,
            2,
            4,
            65,
            9
        ],
        [
            2,
            31,
            40,
            77,
            44,
            69,
            66,
            6,
            9
        ],
        [
            34,
            84,
            84,
            55,
            78,
            21,
            22
        ],
        [
            73,
            1,
            12,
            40,
            50,
            35,
            54,
            3,
            40,
            19,
            89,
            87,
            40,
            59,
            89
        ],
        [
            29,
            35,
            85,
            47,
            14,
            30,
            26,
            71
        ],
        [
            61,
            68,
            8,
            12,
            57,
            54,
            5,
            24,
            85,
            60,
            52,
            77,
            64,
            70
        ],
        [
            61,
            17,
            20,
            78,
            0,
            31,
            45,
            88
        ],
        [
            65,
            38,
            4,
            65,
            48,
            50,
            43,
            16,
            38,
            10,
            10,
            12
        ],
        [
            43,
            58,
            89,
            26,
            62,
            68,
            34,
            62,
            83,
            38,
            31
        ],
        [
            57,
            30,
            39,
            36,
            23
        ],
        [
            79,
            87,
            52,
            12,
            81,
            56
        ],
        [
            27,
            82,
            80,
            34,
            81,
            41,
            51,
            70
        ],
        [
            56,
            41,
            81,
            14,
            23,
            88,
            33,
            3,
            84,
            81,
            48,
            37
        ]
    ],
    "matching": {
        "0": 4,
        "1": 2,
        "2": 4,
        "3": 3,
        "4": 1,
        "5": 2,
        "6": 3,
        "7": 2,
        "8": 2,
        "9": 3,
        "10": 4,
        "11": 2,
        "12": 3,
        "13": 2,
        "14": 2,
        "15": 1,
        "16": 4,
        "17": 0,
        "18": 0,
        "19": 4,
        "20": 2,
        "21": 0,
        "22": 2,
        "23": 1,
        "24": 2,
        "25": 2,
        "26": 2,
        "27": 1,
        "28": 0,
        "29": 3,
        "30": 4,
        "31": 2,
        "32": 0,
        "33": 4,
        "34": 1,
        "35": 1,
        "36": 3,
        "37": 0,
        "38": 4,
        "39": 1,
        "40": 3,
        "41": 1,
        "42": 0,
        "43": 2,
        "44": 1,
        "45": 0,
        "46": 1,
        "47": 4,
        "48": 3,
        "49": 2,
        "50": 1,
        "51": 2,
        "52": 2,
        "53": 0,
        "54": 0,
        "55": 2,
        "56": 0,
        "57": 1,
        "58": 2,
        "59": 1,
        "60": 2,
        "61": 0,
        "62": 1,
        "63": 1,
        "64": 0,
        "65": 1,
        "66": 0,
        "67": 1,
        "68": 0,
        "69": 3,
        "70": 0,
        "71": 3,
        "72": 3,
        "73": 0,
        "74": 1,
        "75": 0,
        "76": 0,
        "77": 3,
        "78": 2,
        "79": 1,
        "80": 0,
        "81": 0,
        "82": 2,
        "83": 3,
        "84": 4,
        "85": 2,
        "86": 2,
        "87": 1,
        "88": 4,
        "89": 4
    },
    "lower_bound": 57.0
}