{
    "node_types": [
        "invoice",
        "sku",
        "zone"
    ],
    "edge_types": [
        "('invoice', 'requires', 'sku')",
        "('sku', 'located_at', 'zone')",
        "('sku', 'rev_requires', 'invoice')",
        "('zone', 'rev_located_at', 'sku')"
    ],
    "num_invoices": 29,
    "num_sku": 98,
    "num_zone": 5,
    "invoices": [
        [
            66,
            18,
            96,
            90,
            5,
            23,
            44,
            89,
            27,
            47,
            39
        ],
        [
            20,
            78,
            33,
            61,
            91,
            14,
            97
        ],
        [
            9,
            44,
            27,
            84,
            47,
            32,
            4,
            62,
            85,
            54
        ],
        [
            75,
            17,
            75,
            21,
            3,
            14,
            78,
            71,
            45,
            56
        ],
        [
            86,
            31,
            12,
            69,
            96,
            86,
            2,
            2,
            78,
            55,
            10,
            38
        ],
        [
            55,
            54,
            46,
            83,
            94,
            32,
            85,
            49,
            65
        ],
        [
            84,
            55,
            41,
            94,
            30,
            10,
            76,
            52,
            80,
            22,
            41,
            43,
            48,
            46
        ],
        [
            8,
            71,
            16,
            57,
            18
        ],
        [
            3,
            52,
            77,
            24,
            39,
            66,
            90,
            81,
            81,
            72,
            93,
            59,
            89,
            67
        ],
        [
            69,
            46,
            14,
            58,
            26,
            17,
            41
        ],
        [
            15,
            91,
            82,
            49,
            53,
            53,
            28,
            67,
            4,
            7,
            82,
            51
        ],
        [
            83,
            30,
            10,
            63,
            40,
            36,
            81,
            88,
            9,
            8
        ],
        [
            53,
            45,
            63,
            16,
            29,
            39,
            90
        ],
        [
            20,
            60,
            36,
            50,
            96,
            62,
            60,
            0,
            70,
            81,
            77,
            29,
            67
        ],
        [
            87,
            66,
            15,
            94,
            86,
            11,
            12
        ],
        [
            89,
            38,
            93,
            42,
            23,
            90,
            37,
            69
        ],
        [
            32,
            68,
            68,
            64,
            91,
            31,
            93,
            2,
            43,
            33,
            79
        ],
        [
            15,
            1,
            7,
            28,
            50,
            44,
            87
        ],
        [
            27,
            88,
            68,
            38,
            31,
            49,
            51,
            70,
            31,
            43,
            48
        ],
        [
            61,
            28,
            64,
            59,
            60,
            45,
            40,
            80,
            59,
            80,
            35,
            38,
            37,
            33
        ],
        [
            87,
            25,
            97,
            94,
            6,
            96,
            95,
            41
        ],
        [
            95,
            48,
            6,
            83,
            18,
            13,
            73,
            58,
            72
        ],
        [
            13,
            70,
            79,
            67,
            34,
            92,
            29,
            73,
            65
        ],
        [
            82,
            33,
            47,
            8,
            22,
            89,
            71,
            92,
            9,
            19,
            21,
            70,
            73,
            75,
            35
        ],
        [
            61,
            88,
            21,
            12,
            74,
            79,
            42,
            76,
            34,
            42,
            36,
            25,
            11
        ],
        [
            55,
            84,
            16,
            64,
            26,
            15,
            74,
            69,
            5
        ],
        [
            47,
            13,
            11,
            19,
            1,
            80,
            17,
            12,
            10,
            56,
            32,
            18,
            20,
            65
        ],
        [
            75,
            87,
            63,
            24,
            22,
            0
        ],
        [
            16,
            72,
            52,
            21,
            76,
            66,
            57
        ]
    ],
    "matching": {
        "0": 0,
        "1": 0,
        "2": 2,
        "3": 4,
        "4": 1,
        "5": 4,
        "6": 3,
        "7": 1,
        "8": 4,
        "9": 1,
        "10": 1,
        "11": 1,
        "12": 0,
        "13": 0,
        "14": 4,
        "15": 4,
        "16": 1,
        "17": 1,
        "18": 1,
        "19": 3,
        "20": 0,
        "21": 2,
        "22": 3,
        "23": 4,
        "24": 3,
        "25": 0,
        "26": 2,
        "27": 4,
        "28": 2,
        "29": 4,
        "30": 0,
        "31": 0,
        "32": 3,
        "33": 4,
        "34": 4,
        "35": 1,
        "36": 2,
        "37": 1,
        "38": 3,
        "39": 3,
        "40": 1,
        "41": 1,
        "42": 2,
        "43": 2,
        "44": 1,
        "45": 3,
        "46": 1,
        "47": 4,
        "48": 4,
        "49": 1,
        "50": 1,
        "51": 1,
        "52": 1,
        "53": 4,
        "54": 4,
        "55": 3,
        "56": 0,
        "57": 0,
        "58": 4,
        "59": 3,
        "60": 3,
        "61": 1,
        "62": 0,
        "63": 4,
        "64": 1,
        "65": 2,
        "66": 1,
        "67": 2,
        "68": 2,
        "69": 2,
        "70": 1,
        "71": 0,
        "72": 4,
        "73": 0,
        "74": 4,
        "75": 1,
        "76": 0,
        "77": 3,
        "78": 0,
        "79": 4,
        "80": 3,
        "81": 3,
        "82": 1,
        "83": 3,
        "84": 1,
        "85": 0,
        "86": 4,
        "87": 1,
        "88": 1,
        "89": 3,
        "90": 2,
        "91": 4,
        "92": 3,
        "93": 3,
        "94": 0,
        "95": 1,
        "96": 0,
        "97": 2
    },
    "lower_bound": 57.0
}