{
    "node_types": [
        "invoice",
        "sku",
        "zone"
    ],
    "edge_types": [
        "('invoice', 'requires', 'sku')",
        "('sku', 'located_at', 'zone')",
        "('sku', 'rev_requires', 'invoice')",
        "('zone', 'rev_located_at', 'sku')"
    ],
    "num_invoices": 32,
    "num_sku": 90,
    "num_zone": 5,
    "invoices": [
        [
            78,
            62,
            82,
            89,
            38
        ],
        [
            60,
            49,
            6,
            9,
            18,
            55,
            51,
            57,
            31,
            85,
            75,
            19,
            39,
            40,
            75,
            32,
            68
        ],
        [
            65,
            8,
            86
        ],
        [
            43,
            3,
            39,
            77,
            36,
            28,
            42,
            76,
            45
        ],
        [
            80,
            87,
            70
        ],
        [
            62,
            24,
            64,
            83,
            56,
            59
        ],
        [
            0,
            88,
            19,
            35,
            46,
            44,
            58,
            85,
            14,
            31,
            26,
            82,
            61,
            80
        ],
        [
            1,
            76,
            82,
            33,
            24,
            15,
            54,
            6,
            81,
            29,
            30
        ],
        [
            63,
            3,
            56,
            17,
            63,
            58,
            6,
            22,
            13,
            21
        ],
        [
            79,
            2,
            20,
            33,
            32,
            37
        ],
        [
            54,
            73,
            69,
            12,
            29,
            80,
            19
        ],
        [
            21,
            40,
            87,
            11,
            37,
            55,
            18,
            18
        ],
        [
            60,
            64,
            13
        ],
        [
            46,
            7,
            55,
            17,
            35
        ],
        [
            4,
            44,
            35,
            57,
            17
        ],
        [
            72,
            58,
            21,
            62,
            79,
            9,
            14,
            74,
            51,
            51,
            26,
            5,
            68
        ],
        [
            39,
            53,
            20,
            20,
            65,
            11
        ],
        [
            16,
            44,
            59,
            64,
            76,
            52,
            0,
            11
        ],
        [
            22,
            7,
            16,
            13,
            2,
            70
        ],
        [
            41,
            8,
            7,
            30,
            34,
            28,
            46,
            0,
            78,
            4
        ],
        [
            30,
            72,
            51,
            22,
            71,
            49,
            45,
            39
        ],
        [
            33,
            67,
            63,
            52,
            15,
            6,
            34
        ],
        [
            69,
            89,
            36,
            80,
            5,
            27,
            84,
            53,
            25
        ],
        [
            83,
            43,
            61,
            65,
            47,
            42,
            82,
            23,
            37,
            43,
            52,
            61
        ],
        [
            79,
            75,
            26,
            59,
            87,
            9,
            24
        ],
        [
            71,
            49,
            60,
            9,
            1,
            64,
            19,
            55,
            43,
            53,
            14,
            86
        ],
        [
            41,
            66,
            77,
            44,
            56,
            89,
            69,
            10,
            13,
            10,
            27,
            71,
            74
        ],
        [
            12,
            57,
            66,
            50,
            50,
            23,
            24
        ],
        [
            60,
            30,
            36,
            25,
            48,
            88,
            29,
            2,
            72,
            83,
            22
        ],
        [
            32,
            73,
            65,
            18,
            84,
            47,
            49,
            62,
            20,
            63,
            59,
            81
        ],
        [
            45,
            16,
            10,
            36,
            67,
            48
        ],
        [
            11,
            47,
            57,
            7,
            31,
            69,
            38,
            28,
            10
        ]
    ],
    "matching": {
        "0": 3,
        "1": 2,
        "2": 0,
        "3": 4,
        "4": 1,
        "5": 0,
        "6": 4,
        "7": 0,
        "8": 0,
        "9": 4,
        "10": 1,
        "11": 1,
        "12": 4,
        "13": 1,
        "14": 3,
        "15": 0,
        "16": 0,
        "17": 0,
        "18": 4,
        "19": 1,
        "20": 2,
        "21": 3,
        "22": 1,
        "23": 2,
        "24": 1,
        "25": 2,
        "26": 1,
        "27": 3,
        "28": 4,
        "29": 4,
        "30": 1,
        "31": 0,
        "32": 3,
        "33": 3,
        "34": 3,
        "35": 3,
        "36": 0,
        "37": 3,
        "38": 3,
        "39": 0,
        "40": 2,
        "41": 0,
        "42": 1,
        "43": 1,
        "44": 2,
        "45": 3,
        "46": 2,
        "47": 1,
        "48": 1,
        "49": 1,
        "50": 1,
        "51": 0,
        "52": 1,
        "53": 3,
        "54": 4,
        "55": 2,
        "56": 1,
        "57": 4,
        "58": 4,
        "59": 3,
        "60": 0,
        "61": 2,
        "62": 2,
        "63": 0,
        "64": 4,
        "65": 4,
        "66": 1,
        "67": 3,
        "68": 4,
        "69": 1,
        "70": 0,
        "71": 2,
        "72": 4,
        "73": 2,
        "74": 2,
        "75": 2,
        "76": 1,
        "77": 2,
        "78": 3,
        "79": 2,
        "80": 3,
        "81": 4,
        "82": 0,
        "83": 0,
        "84": 0,
        "85": 0,
        "86": 3,
        "87": 3,
        "88": 0,
        "89": 3
    },
    "lower_bound": 63.0
}