{
    "node_types": [
        "invoice",
        "sku",
        "zone"
    ],
    "edge_types": [
        "('invoice', 'requires', 'sku')",
        "('sku', 'located_at', 'zone')",
        "('sku', 'rev_requires', 'invoice')",
        "('zone', 'rev_located_at', 'sku')"
    ],
    "num_invoices": 33,
    "num_sku": 71,
    "num_zone": 5,
    "invoices": [
        [
            43,
            44,
            61,
            5,
            67,
            35,
            67,
            65,
            33,
            69,
            41,
            43
        ],
        [
            58,
            50,
            63,
            37,
            41,
            68,
            57
        ],
        [
            45,
            39,
            68,
            40,
            42,
            15
        ],
        [
            29,
            51,
            46,
            11
        ],
        [
            20,
            24,
            37,
            1,
            16,
            5
        ],
        [
            28,
            55,
            62,
            24,
            59
        ],
        [
            33,
            13,
            38,
            17,
            25,
            54,
            68,
            27,
            37
        ],
        [
            3,
            27,
            11,
            7,
            62,
            6,
            61,
            25,
            30,
            20,
            22,
            50,
            20,
            49,
            21
        ],
        [
            20,
            66,
            6,
            30,
            34,
            66,
            15,
            18
        ],
        [
            66,
            1,
            8,
            19,
            54,
            62
        ],
        [
            22,
            41,
            51,
            12,
            53
        ],
        [
            14,
            44,
            3,
            39,
            14
        ],
        [
            59,
            63,
            18,
            67,
            56,
            51,
            14,
            11
        ],
        [
            10,
            32,
            19,
            39
        ],
        [
            29,
            1,
            42,
            22,
            66,
            0
        ],
        [
            46,
            24,
            65,
            48,
            33,
            36,
            17
        ],
        [
            56,
            35,
            35,
            26,
            21
        ],
        [
            45,
            31,
            64,
            38
        ],
        [
            49,
            63,
            13,
            22,
            41,
            23
        ],
        [
            49,
            34,
            56,
            7,
            33,
            11
        ],
        [
            48,
            2,
            48,
            21,
            29,
            28,
            5,
            27
        ],
        [
            54,
            44,
            5
        ],
        [
            64,
            61,
            70,
            54,
            69,
            17,
            8
        ],
        [
            19,
            37,
            44,
            0,
            50
        ],
        [
            42,
            29,
            26,
            60,
            69,
            31,
            60
        ],
        [
            60,
            61,
            51,
            4,
            53,
            67
        ],
        [
            32,
            1,
            16,
            59,
            52
        ],
        [
            47,
            35,
            23,
            62,
            2,
            28,
            9
        ],
        [
            8,
            23,
            64,
            30,
            12,
            56,
            14,
            9
        ],
        [
            40,
            19,
            48,
            7,
            10,
            18,
            46
        ],
        [
            36,
            4,
            52,
            55,
            47
        ],
        [
            12,
            27,
            58,
            34,
            34,
            57,
            38
        ],
        [
            42,
            0,
            70,
            46
        ]
    ],
    "matching": {
        "0": 1,
        "1": 0,
        "2": 0,
        "3": 0,
        "4": 0,
        "5": 1,
        "6": 3,
        "7": 4,
        "8": 1,
        "9": 3,
        "10": 4,
        "11": 3,
        "12": 3,
        "13": 2,
        "14": 3,
        "15": 3,
        "16": 4,
        "17": 0,
        "18": 4,
        "19": 3,
        "20": 0,
        "21": 1,
        "22": 4,
        "23": 3,
        "24": 0,
        "25": 3,
        "26": 0,
        "27": 1,
        "28": 1,
        "29": 0,
        "30": 4,
        "31": 0,
        "32": 1,
        "33": 2,
        "34": 1,
        "35": 1,
        "36": 3,
        "37": 2,
        "38": 2,
        "39": 0,
        "40": 2,
        "41": 4,
        "42": 4,
        "43": 0,
        "44": 3,
        "45": 2,
        "46": 4,
        "47": 1,
        "48": 0,
        "49": 1,
        "50": 4,
        "51": 4,
        "52": 0,
        "53": 0,
        "54": 0,
        "55": 4,
        "56": 2,
        "57": 0,
        "58": 2,
        "59": 1,
        "60": 1,
        "61": 1,
        "62": 0,
        "63": 4,
        "64": 2,
        "65": 1,
        "66": 2,
        "67": 0,
        "68": 2,
        "69": 1,
        "70": 2
    },
    "lower_bound": 57.0
}