{
    "node_types": [
        "invoice",
        "sku",
        "zone"
    ],
    "edge_types": [
        "('invoice', 'requires', 'sku')",
        "('sku', 'located_at', 'zone')",
        "('sku', 'rev_requires', 'invoice')",
        "('zone', 'rev_located_at', 'sku')"
    ],
    "num_invoices": 30,
    "num_sku": 89,
    "num_zone": 5,
    "invoices": [
        [
            78,
            58,
            76,
            48,
            46,
            62
        ],
        [
            61,
            81,
            26,
            9,
            6,
            33,
            16,
            18,
            8,
            51,
            86,
            23,
            54
        ],
        [
            27,
            49,
            40,
            73,
            18,
            3,
            28
        ],
        [
            2,
            35,
            75,
            71,
            64,
            41,
            47,
            17,
            37,
            53
        ],
        [
            38,
            22,
            29,
            68,
            25,
            71,
            65,
            67,
            1
        ],
        [
            10,
            77,
            20,
            44,
            69,
            72,
            87,
            8
        ],
        [
            57,
            51,
            22,
            25,
            70,
            83,
            53,
            61
        ],
        [
            38,
            17,
            31,
            1,
            9,
            0,
            30,
            80
        ],
        [
            81,
            9,
            4,
            36,
            50,
            35,
            20,
            79
        ],
        [
            11,
            57,
            44,
            21,
            86,
            23
        ],
        [
            20,
            59,
            9,
            41,
            77,
            40,
            32
        ],
        [
            55,
            67,
            80,
            15,
            43,
            12,
            79,
            33,
            26,
            76,
            47
        ],
        [
            69,
            37,
            82,
            27,
            85
        ],
        [
            46,
            73,
            30,
            37,
            68,
            40,
            87
        ],
        [
            21,
            52,
            64,
            50,
            44,
            41,
            84,
            56,
            17,
            28,
            75
        ],
        [
            59,
            1,
            23,
            33,
            62,
            81,
            42,
            56,
            24,
            69,
            43,
            3,
            20,
            39,
            77
        ],
        [
            6,
            73,
            35,
            16,
            33,
            21,
            10,
            46,
            58
        ],
        [
            59,
            63,
            76,
            75,
            85,
            77,
            60,
            30,
            26
        ],
        [
            60,
            19,
            43,
            29,
            66,
            12,
            81,
            74,
            16,
            69,
            53
        ],
        [
            65,
            30,
            28,
            1
        ],
        [
            13,
            2,
            60,
            88,
            7,
            5,
            84
        ],
        [
            85,
            68,
            40,
            15,
            86,
            21,
            2,
            86,
            29,
            17,
            66,
            68
        ],
        [
            53,
            45,
            65,
            5,
            8,
            13,
            2,
            52,
            44
        ],
        [
            39,
            45,
            49,
            70,
            65,
            78,
            11,
            48,
            85
        ],
        [
            64,
            3,
            84,
            32,
            38,
            63,
            45,
            0,
            70
        ],
        [
            78,
            67,
            79,
            10,
            14,
            54,
            18,
            24,
            82,
            57,
            47,
            24
        ],
        [
            55,
            24,
            27,
            34,
            58,
            60,
            48,
            47,
            48,
            28,
            84
        ],
        [
            3,
            10,
            15,
            41,
            22,
            56,
            52,
            74,
            72,
            19,
            14
        ],
        [
            26,
            18,
            56,
            36,
            64,
            78,
            31,
            29,
            43,
            42,
            36,
            34,
            31,
            6
        ],
        [
            27,
            7,
            4,
            74,
            57,
            4,
            49,
            83,
            75,
            80,
            37,
            8,
            11,
            88,
            82
        ]
    ],
    "matching": {
        "0": 4,
        "1": 4,
        "2": 4,
        "3": 1,
        "4": 2,
        "5": 0,
        "6": 2,
        "7": 3,
        "8": 3,
        "9": 0,
        "10": 2,
        "11": 4,
        "12": 0,
        "13": 2,
        "14": 0,
        "15": 0,
        "16": 2,
        "17": 3,
        "18": 4,
        "19": 2,
        "20": 1,
        "21": 0,
        "22": 3,
        "23": 4,
        "24": 0,
        "25": 4,
        "26": 0,
        "27": 3,
        "28": 2,
        "29": 4,
        "30": 4,
        "31": 1,
        "32": 3,
        "33": 0,
        "34": 4,
        "35": 0,
        "36": 4,
        "37": 0,
        "38": 1,
        "39": 0,
        "40": 0,
        "41": 4,
        "42": 3,
        "43": 4,
        "44": 4,
        "45": 3,
        "46": 0,
        "47": 1,
        "48": 1,
        "49": 0,
        "50": 0,
        "51": 2,
        "52": 2,
        "53": 3,
        "54": 3,
        "55": 4,
        "56": 0,
        "57": 2,
        "58": 0,
        "59": 3,
        "60": 4,
        "61": 0,
        "62": 4,
        "63": 3,
        "64": 0,
        "65": 2,
        "66": 0,
        "67": 0,
        "68": 3,
        "69": 4,
        "70": 3,
        "71": 1,
        "72": 2,
        "73": 4,
        "74": 1,
        "75": 4,
        "76": 4,
        "77": 0,
        "78": 4,
        "79": 2,
        "80": 3,
        "81": 4,
        "82": 4,
        "83": 0,
        "84": 4,
        "85": 0,
        "86": 2,
        "87": 0,
        "88": 2
    },
    "lower_bound": 57.0
}