{
    "node_types": [
        "invoice",
        "sku",
        "zone"
    ],
    "edge_types": [
        "('invoice', 'requires', 'sku')",
        "('sku', 'located_at', 'zone')",
        "('sku', 'rev_requires', 'invoice')",
        "('zone', 'rev_located_at', 'sku')"
    ],
    "num_invoices": 31,
    "num_sku": 53,
    "num_zone": 5,
    "invoices": [
        [
            9,
            33,
            14,
            29,
            12,
            39,
            16,
            41,
            6,
            3,
            34
        ],
        [
            19,
            31
        ],
        [
            11,
            23,
            47,
            21,
            25,
            11,
            28,
            46
        ],
        [
            14,
            40,
            34,
            37,
            38
        ],
        [
            15,
            32,
            16,
            10,
            21,
            52,
            28
        ],
        [
            52,
            36,
            37,
            5
        ],
        [
            15,
            45,
            4,
            9,
            20
        ],
        [
            9,
            6,
            20,
            48,
            44
        ],
        [
            31,
            13,
            8,
            47,
            5,
            26
        ],
        [
            20,
            37,
            20,
            29,
            33,
            39,
            11
        ],
        [
            13,
            11,
            3,
            0,
            51,
            10,
            35
        ],
        [
            52,
            32,
            21,
            12
        ],
        [
            49,
            47,
            22,
            40,
            1
        ],
        [
            44,
            40,
            38,
            44
        ],
        [
            40,
            13,
            2,
            15,
            50
        ],
        [
            25,
            19,
            22,
            26,
            31
        ],
        [
            5,
            22,
            8,
            34,
            45
        ],
        [
            2
        ],
        [
            21,
            5,
            51,
            49
        ],
        [
            18,
            50,
            14,
            1
        ],
        [
            18,
            42,
            7,
            35,
            48,
            30
        ],
        [
            48,
            29,
            0
        ],
        [
            41,
            14,
            52,
            46,
            27,
            23
        ],
        [
            6,
            43,
            33
        ],
        [
            1,
            4,
            25,
            27
        ],
        [
            17,
            36,
            2,
            30,
            6,
            48,
            15,
            12
        ],
        [
            17,
            36,
            25,
            0
        ],
        [
            24,
            42,
            7,
            45,
            44,
            24,
            17,
            33
        ],
        [
            43,
            19,
            16,
            4,
            28
        ],
        [
            3,
            9,
            8,
            43,
            42
        ],
        [
            10,
            23,
            8,
            30
        ]
    ],
    "matching": {
        "0": 0,
        "1": 4,
        "2": 0,
        "3": 1,
        "4": 2,
        "5": 3,
        "6": 2,
        "7": 0,
        "8": 0,
        "9": 3,
        "10": 1,
        "11": 2,
        "12": 1,
        "13": 1,
        "14": 1,
        "15": 1,
        "16": 2,
        "17": 2,
        "18": 4,
        "19": 1,
        "20": 3,
        "21": 3,
        "22": 0,
        "23": 1,
        "24": 0,
        "25": 3,
        "26": 2,
        "27": 0,
        "28": 2,
        "29": 0,
        "30": 4,
        "31": 3,
        "32": 1,
        "33": 4,
        "34": 2,
        "35": 3,
        "36": 1,
        "37": 1,
        "38": 0,
        "39": 3,
        "40": 0,
        "41": 2,
        "42": 1,
        "43": 0,
        "44": 4,
        "45": 3,
        "46": 2,
        "47": 2,
        "48": 2,
        "49": 2,
        "50": 0,
        "51": 3,
        "52": 3
    },
    "lower_bound": 45.0
}