{
    "node_types": [
        "invoice",
        "sku",
        "zone"
    ],
    "edge_types": [
        "('invoice', 'requires', 'sku')",
        "('sku', 'located_at', 'zone')",
        "('sku', 'rev_requires', 'invoice')",
        "('zone', 'rev_located_at', 'sku')"
    ],
    "num_invoices": 27,
    "num_sku": 99,
    "num_zone": 5,
    "invoices": [
        [
            98,
            1,
            26,
            86,
            33,
            1,
            78,
            84,
            32,
            28,
            19
        ],
        [
            44,
            12,
            8,
            75,
            86,
            41,
            48,
            4,
            74,
            47,
            89,
            26,
            59,
            30
        ],
        [
            1,
            52,
            32,
            93,
            82
        ],
        [
            90,
            76,
            35,
            73,
            62,
            70
        ],
        [
            52,
            31,
            77,
            23,
            49,
            80,
            31,
            87,
            28,
            21,
            33
        ],
        [
            38,
            58,
            25,
            57,
            79,
            91,
            39,
            94
        ],
        [
            38,
            18,
            58,
            46,
            57,
            45,
            50,
            41,
            68,
            70,
            42,
            62,
            63,
            88,
            23
        ],
        [
            92,
            61,
            87,
            38,
            89,
            49
        ],
        [
            67,
            36,
            79,
            13,
            4,
            11,
            25,
            37,
            20,
            4,
            5,
            34,
            60,
            70,
            66,
            14
        ],
        [
            94,
            51,
            93,
            24,
            42,
            45,
            88,
            36,
            10,
            87
        ],
        [
            62,
            97,
            89,
            7,
            40,
            17
        ],
        [
            62,
            91,
            7,
            23,
            43,
            66,
            72,
            65,
            77,
            2,
            76,
            44
        ],
        [
            78,
            40,
            64,
            81,
            81,
            59,
            20,
            55,
            24,
            82,
            6,
            39
        ],
        [
            7,
            65,
            13,
            53,
            60,
            51,
            44
        ],
        [
            90,
            92,
            44,
            87,
            36,
            8,
            69
        ],
        [
            37,
            28,
            14,
            76,
            46,
            63,
            9,
            95,
            3,
            84,
            58,
            85,
            56,
            59
        ],
        [
            77,
            61,
            95,
            85,
            71,
            97,
            18,
            68,
            82,
            78,
            0,
            12
        ],
        [
            47,
            49,
            67,
            89,
            60,
            55
        ],
        [
            35,
            6,
            83,
            7,
            6,
            21,
            29,
            0,
            64,
            94,
            67
        ],
        [
            75,
            91,
            77,
            16,
            5,
            54,
            36,
            53,
            88,
            55,
            0
        ],
        [
            5,
            33,
            15,
            2,
            96,
            19,
            80,
            12,
            27,
            51,
            12,
            25,
            29,
            40,
            14,
            98
        ],
        [
            29,
            34,
            69,
            15,
            3,
            32,
            80,
            96,
            27,
            4,
            74,
            46,
            56,
            47
        ],
        [
            84,
            72,
            39,
            59,
            10,
            95,
            5,
            69
        ],
        [
            2,
            48,
            18,
            30,
            75,
            20,
            25,
            73,
            64,
            81,
            83,
            41,
            71
        ],
        [
            26,
            29,
            72,
            73,
            8,
            50,
            91,
            22,
            22,
            16,
            90,
            24,
            2
        ],
        [
            95,
            54,
            21,
            11,
            43,
            35,
            17,
            6,
            64,
            92,
            33
        ],
        [
            61,
            88,
            18,
            69,
            23,
            98,
            26,
            9,
            53,
            11,
            14,
            94
        ]
    ],
    "matching": {
        "0": 0,
        "1": 0,
        "2": 3,
        "3": 3,
        "4": 2,
        "5": 3,
        "6": 3,
        "7": 4,
        "8": 3,
        "9": 3,
        "10": 0,
        "11": 1,
        "12": 1,
        "13": 0,
        "14": 4,
        "15": 1,
        "16": 2,
        "17": 2,
        "18": 2,
        "19": 0,
        "20": 3,
        "21": 4,
        "22": 3,
        "23": 0,
        "24": 2,
        "25": 1,
        "26": 3,
        "27": 4,
        "28": 2,
        "29": 3,
        "30": 2,
        "31": 4,
        "32": 0,
        "33": 4,
        "34": 1,
        "35": 0,
        "36": 2,
        "37": 0,
        "38": 0,
        "39": 4,
        "40": 4,
        "41": 2,
        "42": 3,
        "43": 4,
        "44": 3,
        "45": 1,
        "46": 0,
        "47": 1,
        "48": 2,
        "49": 0,
        "50": 2,
        "51": 0,
        "52": 3,
        "53": 4,
        "54": 2,
        "55": 1,
        "56": 3,
        "57": 4,
        "58": 0,
        "59": 1,
        "60": 4,
        "61": 2,
        "62": 4,
        "63": 0,
        "64": 2,
        "65": 4,
        "66": 3,
        "67": 4,
        "68": 4,
        "69": 2,
        "70": 1,
        "71": 1,
        "72": 2,
        "73": 1,
        "74": 0,
        "75": 3,
        "76": 4,
        "77": 3,
        "78": 2,
        "79": 4,
        "80": 3,
        "81": 2,
        "82": 2,
        "83": 1,
        "84": 4,
        "85": 2,
        "86": 2,
        "87": 1,
        "88": 0,
        "89": 2,
        "90": 3,
        "91": 2,
        "92": 3,
        "93": 2,
        "94": 3,
        "95": 3,
        "96": 3,
        "97": 4,
        "98": 3
    },
    "lower_bound": 60.0
}